bt4vt/__init__.py
bt4vt/core.py
bt4vt/dataio.py
bt4vt/dataset_evaluate.py
bt4vt/evaluate.py
bt4vt/groups.py
bt4vt/metrics.py
bt4vt/parked_functions.py
bt4vt/voxceleb.py
bt4vt/data/config.yaml
bt4vt/data/resnetse34l_H-eval_scores.csv
bt4vt/data/resnetse34v2_H-eval_scores.csv
bt4vt/data/vox1_meta.csv
bt4vt-1.0.1.dist-info/LICENSE
bt4vt-1.0.1.dist-info/METADATA
bt4vt-1.0.1.dist-info/WHEEL
bt4vt-1.0.1.dist-info/top_level.txt
bt4vt-1.0.1.dist-info/RECORD
