Metadata-Version: 2.1
Name: bt4vt
Version: 1.0.1
Summary: Bias Tests for Voice Technologies
Home-page: https://github.com/wiebket/bt4vt
Author: Wiebke Hutiri, Anna Leschanowsky
Author-email: wiebke.toussaint@gmail.com
License: GPL-3.0-or-later
Classifier: Programming Language :: Python :: 3
Classifier: Development Status :: 2 - Pre-Alpha
Classifier: License :: OSI Approved :: GNU General Public License v3 or later (GPLv3+)
Classifier: Natural Language :: English
License-File: LICENSE
Requires-Dist: numpy
Requires-Dist: pandas
Requires-Dist: PyYAML
Requires-Dist: scikit-learn
Requires-Dist: scipy
Requires-Dist: setuptools
Requires-Dist: importlib-resources
Provides-Extra: dev
Requires-Dist: flake8 ; extra == 'dev'
Requires-Dist: pytest ; extra == 'dev'
Requires-Dist: pytest-cov ; extra == 'dev'
